[
  {
    "symbol": "KOG.OL",
    "signal": "BUY",
    "score": 9.5,
    "entry": 412.7,
    "stop": 371.43,
    "target": 495.24,
    "rr": 2.0,
    "rsi": 66.52,
    "volumeRatio": 0.33,
    "change20d": 11.27,
    "positionShares": 4,
    "positionValue": 1650.8,
    "comment": "KOG.OL: sterk trend, RSI 66.5, normalt volum, nær breakout.",
    "scanDate": "2026-03-16T12:49:43.155660Z"
  },
  {
    "symbol": "NOD.OL",
    "signal": "BUY",
    "score": 9.0,
    "entry": 159.8,
    "stop": 143.82,
    "target": 191.76,
    "rr": 2.0,
    "rsi": 66.46,
    "volumeRatio": 0.94,
    "change20d": 13.33,
    "positionShares": 12,
    "positionValue": 1917.6,
    "comment": "NOD.OL: sterk trend, RSI 66.5, normalt volum, nær breakout.",
    "scanDate": "2026-03-16T12:49:51.963429Z"
  },
  {
    "symbol": "NHY.OL",
    "signal": "BUY",
    "score": 8.5,
    "entry": 95.42,
    "stop": 85.88,
    "target": 114.5,
    "rr": 2.0,
    "rsi": 62.78,
    "volumeRatio": 0.22,
    "change20d": 13.0,
    "positionShares": 20,
    "positionValue": 1908.4,
    "comment": "NHY.OL: sterk trend, RSI 62.8, normalt volum, under breakout-nivå.",
    "scanDate": "2026-03-16T12:49:43.755811Z"
  },
  {
    "symbol": "LSG.OL",
    "signal": "BUY",
    "score": 8.5,
    "entry": 50.85,
    "stop": 47.8,
    "target": 56.95,
    "rr": 2.0,
    "rsi": 57.64,
    "volumeRatio": 0.38,
    "change20d": 3.86,
    "positionShares": 65,
    "positionValue": 3305.25,
    "comment": "LSG.OL: sterk trend, RSI 57.6, normalt volum, under breakout-nivå.",
    "scanDate": "2026-03-16T12:49:47.991812Z"
  },
  {
    "symbol": "MPCC.OL",
    "signal": "BUY",
    "score": 8.5,
    "entry": 22.44,
    "stop": 20.2,
    "target": 26.93,
    "rr": 2.0,
    "rsi": 60.18,
    "volumeRatio": 0.34,
    "change20d": 15.97,
    "positionShares": 89,
    "positionValue": 1997.16,
    "comment": "MPCC.OL: sterk trend, RSI 60.2, normalt volum, under breakout-nivå.",
    "scanDate": "2026-03-16T12:49:53.388046Z"
  },
  {
    "symbol": "BWE.OL",
    "signal": "BUY",
    "score": 8.0,
    "entry": 56.3,
    "stop": 50.67,
    "target": 67.56,
    "rr": 2.0,
    "rsi": 65.64,
    "volumeRatio": 0.47,
    "change20d": 20.82,
    "positionShares": 35,
    "positionValue": 1970.5,
    "comment": "BWE.OL: sterk trend, RSI 65.6, normalt volum, under breakout-nivå.",
    "scanDate": "2026-03-16T12:49:47.137980Z"
  },
  {
    "symbol": "ODL.OL",
    "signal": "BUY",
    "score": 8.0,
    "entry": 101.6,
    "stop": 96.02,
    "target": 112.76,
    "rr": 2.0,
    "rsi": 53.32,
    "volumeRatio": 0.25,
    "change20d": -0.39,
    "positionShares": 35,
    "positionValue": 3556.0,
    "comment": "ODL.OL: sterk trend, RSI 53.3, normalt volum, under breakout-nivå.",
    "scanDate": "2026-03-16T12:49:48.987385Z"
  },
  {
    "symbol": "VEI.OL",
    "signal": "BUY",
    "score": 8.0,
    "entry": 192.2,
    "stop": 186.43,
    "target": 203.73,
    "rr": 2.0,
    "rsi": 54.86,
    "volumeRatio": 0.91,
    "change20d": 1.48,
    "positionShares": 20,
    "positionValue": 3844.0,
    "comment": "VEI.OL: sterk trend, RSI 54.9, normalt volum, under breakout-nivå.",
    "scanDate": "2026-03-16T12:49:50.510055Z"
  },
  {
    "symbol": "SOFF.OL",
    "signal": "BUY",
    "score": 7.5,
    "entry": 57.1,
    "stop": 51.39,
    "target": 68.52,
    "rr": 2.0,
    "rsi": 66.03,
    "volumeRatio": 0.2,
    "change20d": 16.29,
    "positionShares": 35,
    "positionValue": 1998.5,
    "comment": "SOFF.OL: sterk trend, RSI 66.0, normalt volum, under breakout-nivå.",
    "scanDate": "2026-03-16T12:49:55.781813Z"
  },
  {
    "symbol": "AKRBP.OL",
    "signal": "WATCH",
    "score": 8.0,
    "entry": 331.8,
    "stop": 298.62,
    "target": 398.16,
    "rr": 2.0,
    "rsi": 75.08,
    "volumeRatio": 0.59,
    "change20d": 22.8,
    "positionShares": 6,
    "positionValue": 1990.8,
    "comment": "AKRBP.OL: interessant oppsett, men trenger bekreftelse. RSI 75.1, normalt volum.",
    "scanDate": "2026-03-16T12:49:43.329823Z"
  },
  {
    "symbol": "PROT.OL",
    "signal": "WATCH",
    "score": 8.0,
    "entry": 523.0,
    "stop": 483.07,
    "target": 602.86,
    "rr": 2.0,
    "rsi": 56.17,
    "volumeRatio": 0.65,
    "change20d": 6.09,
    "positionShares": 5,
    "positionValue": 2615.0,
    "comment": "PROT.OL: interessant oppsett, men trenger bekreftelse. RSI 56.2, normalt volum.",
    "scanDate": "2026-03-16T12:49:54.913906Z"
  },
  {
    "symbol": "DNB.OL",
    "signal": "WATCH",
    "score": 7.0,
    "entry": 290.7,
    "stop": 281.98,
    "target": 308.14,
    "rr": 2.0,
    "rsi": 46.87,
    "volumeRatio": 0.23,
    "change20d": -1.96,
    "positionShares": 13,
    "positionValue": 3779.1,
    "comment": "DNB.OL: interessant oppsett, men trenger bekreftelse. RSI 46.9, normalt volum.",
    "scanDate": "2026-03-16T12:49:42.907897Z"
  },
  {
    "symbol": "TEL.OL",
    "signal": "WATCH",
    "score": 7.0,
    "entry": 172.2,
    "stop": 166.76,
    "target": 183.08,
    "rr": 2.0,
    "rsi": 56.64,
    "volumeRatio": 0.2,
    "change20d": -2.77,
    "positionShares": 23,
    "positionValue": 3960.6,
    "comment": "TEL.OL: interessant oppsett, men trenger bekreftelse. RSI 56.6, normalt volum.",
    "scanDate": "2026-03-16T12:49:45.705958Z"
  },
  {
    "symbol": "SALM.OL",
    "signal": "WATCH",
    "score": 7.0,
    "entry": 592.0,
    "stop": 537.8,
    "target": 700.4,
    "rr": 2.0,
    "rsi": 58.01,
    "volumeRatio": 0.26,
    "change20d": 1.72,
    "positionShares": 3,
    "positionValue": 1776.0,
    "comment": "SALM.OL: interessant oppsett, men trenger bekreftelse. RSI 58.0, normalt volum.",
    "scanDate": "2026-03-16T12:49:46.023947Z"
  },
  {
    "symbol": "SUBC.OL",
    "signal": "WATCH",
    "score": 7.0,
    "entry": 253.8,
    "stop": 237.81,
    "target": 285.79,
    "rr": 2.0,
    "rsi": 50.67,
    "volumeRatio": 0.21,
    "change20d": -0.39,
    "positionShares": 12,
    "positionValue": 3045.6,
    "comment": "SUBC.OL: interessant oppsett, men trenger bekreftelse. RSI 50.7, normalt volum.",
    "scanDate": "2026-03-16T12:49:46.282033Z"
  }
]